neutrowater/__init__.py
neutrowater/data/H_angular.txt
neutrowater/data/O_angular.txt
neutrowater/data/O_cross.pdf
neutrowater/data/__init__.py
neutrowater/data/h_cross_a.txt
neutrowater/data/h_cross_s.txt
neutrowater/data/h_cross_t.txt
neutrowater/data/mean_free_path.csv
neutrowater/data/neutron_spectrum.txt
neutrowater/data/neutron_spectrum_normalized.txt
neutrowater/data/o_cross_a.txt
neutrowater/data/o_cross_s.txt
neutrowater/data/o_cross_t.txt
neutrowater/diffusing_neutrons.py
neutrowater/models/__init__.py
neutrowater/models/collisions.py
neutrowater/models/maxwell_boltzmann.py
neutrowater/models/neutrons.py
neutrowater/models/tank.py
neutrowater/post_measure.py
neutrowater/process/__init__.py
neutrowater/process/angular_processor.py
neutrowater/process/data_processor.py
neutrowater-0.0.3.dist-info/LICENSE
neutrowater-0.0.3.dist-info/METADATA
neutrowater-0.0.3.dist-info/WHEEL
neutrowater-0.0.3.dist-info/RECORD
