Metadata-Version: 2.1
Name: NeutroWater
Version: 0.0.3
Summary: Monte Carlo simulation of neutron moderation
Author: DerkNiessink
Author-email: derk@niessink.com
Requires-Python: >=3.10,<4.0
Classifier: Programming Language :: Python :: 3
Classifier: Programming Language :: Python :: 3.10
Classifier: Programming Language :: Python :: 3.11
Classifier: Programming Language :: Python :: 3.12
Requires-Dist: brokenaxes (>=0.6.0,<0.7.0)
Requires-Dist: build (>=1.2.1,<2.0.0)
Requires-Dist: ipykernel (>=6.29.1,<7.0.0)
Requires-Dist: ipywidgets (>=8.1.2,<9.0.0)
Requires-Dist: matplotlib (>=3.8.2,<4.0.0)
Requires-Dist: mkdocs (>=1.6.0,<2.0.0)
Requires-Dist: mkdocs-glightbox (>=0.3.7,<0.4.0)
Requires-Dist: numba (>=0.59.0,<0.60.0)
Requires-Dist: numpy (>=1.26.4,<2.0.0)
Requires-Dist: pandas (>=2.2.0,<3.0.0)
Requires-Dist: pymdown-extensions (>=10.8,<11.0)
Requires-Dist: pytest (>=8.0.0,<9.0.0)
Requires-Dist: ruff (>=0.2.1,<0.3.0)
Requires-Dist: scienceplots (>=2.1.1,<3.0.0)
Requires-Dist: scipy (>=1.12.0,<2.0.0)
Requires-Dist: seaborn (>=0.13.2,<0.14.0)
Requires-Dist: tqdm (>=4.66.2,<5.0.0)
